ProtView.py
prot_view-0.0.1.dist-info/LICENSE.txt
prot_view-0.0.1.dist-info/METADATA
prot_view-0.0.1.dist-info/WHEEL
prot_view-0.0.1.dist-info/top_level.txt
prot_view-0.0.1.dist-info/RECORD
